nvm/__init__.py
nvm/_version.py
nvm/nvm.py
nvm/aux_log/__init__.py
nvm/aux_log/aux_log.py
nvm/aux_pandas/__init__.py
nvm/aux_pandas/aux_pandas.py
nvm/aux_spacy/__init__.py
nvm/aux_spacy/aux_spacy.py
nvm/aux_spacy/set_container_extensions.py
nvm/aux_spacy/data/__init__.py
nvm/aux_spacy/data/NicolasEtAl2019a/__init__.py
nvm/aux_spacy/data/NicolasEtAl2019a/data.json
nvm/aux_spacy/data/PennebakerEtAl2015a/.gitignore
nvm/aux_spacy/data/PennebakerEtAl2015a/__init__.py
nvm/aux_spacy/data/PietraszkiewiczEtAl2019a/__init__.py
nvm/aux_spacy/data/PietraszkiewiczEtAl2019a/data.json
nvm/aux_spacy/data/PietraszkiewiczEtAl2019a/data_liwc.json
nvm/aux_spacy/factories/__init__.py
nvm/aux_spacy/factories/get_doc_basic_metrics.py
nvm/aux_spacy/factories/get_doc_count_of_dict_items.py
nvm/aux_spacy/factories/get_doc_sentences.py
nvm/aux_spacy/factories/get_doc_summary_dict.py
nvm/aux_spacy/factories/get_doc_word_count.py
nvm/aux_srsly/__init__.py
nvm/aux_srsly/aux_srsly.py
nvm/aux_str/__init__.py
nvm/aux_str/aux_str.py
nvm/aux_str/clean_str_mappings.py
nvm/aux_str/regex.py
nvm/aux_sys/__init__.py
nvm/aux_sys/aux_sys.py
nvm/cli/.gitkeep
nvm/cli/__init__.py
nvm/cli/nvm.py
nvm/data/.gitkeep
nvm/data/emacs-logo/emacs-128x128.png
nvm/data/emacs-logo/emacs.svg
nvm/tests/__init__.py
nvm/tests/test_aux_spacy.py
nvm/tests/test_aux_str.py
nvm/tests/test_nvm.py
nvm-1.0.21.dist-info/AUTHORS.rst
nvm-1.0.21.dist-info/LICENSE
nvm-1.0.21.dist-info/METADATA
nvm-1.0.21.dist-info/WHEEL
nvm-1.0.21.dist-info/entry_points.txt
nvm-1.0.21.dist-info/top_level.txt
nvm-1.0.21.dist-info/RECORD
