Metadata-Version: 2.1
Name: nvm
Version: 1.0.21
Summary: Plenty little helpers.
Home-page: https://github.com/cogsys-io/nvm
Author: cogsys.io
Author-email: cogsys@cogsys.io
License: GNU General Public License v3
Keywords: nvm
Classifier: Development Status :: 2 - Pre-Alpha
Classifier: Intended Audience :: Developers
Classifier: License :: OSI Approved :: GNU General Public License v3 (GPLv3)
Classifier: Natural Language :: English
Classifier: Programming Language :: Python :: 3
Classifier: Programming Language :: Python :: 3.8
Requires-Python: >=3.8
Provides-Extra: setup
Provides-Extra: test
Provides-Extra: dev
Provides-Extra: all
License-File: LICENSE
License-File: AUTHORS.rst
